databases/__init__.py
databases/corus_databases_daily.py
databases/corus_databases_hourly.py
databases/corus_databases_interval.py
databases/corus_databases_monthly.py
databases/corus_parameter_map_046.py
databases/corus_parameter_map_054.py
databases/corus_parameter_map_057.py
databases/corus_parameter_map_059.py
databases/corus_parameter_map_062.py
databases/corus_parameter_map_065.py
databases/corus_parameter_map_068.py
databases/corus_parameter_map_071.py
databases/corus_parameter_map_200.py
databases/corus_parameter_map_G5B00.py
databases/corus_parameter_map_I5B00.py
databases/corus_parameter_map_M5A00.py
databases/corus_parameter_map_M5A02.py
databases/corus_parameter_map_M5A03.py
databases/corus_parameter_map_M5A04.py
databases/corus_parameter_map_V1003.py
databases/corus_parameter_map_b0038.py
databases/corus_parameter_map_b0039.py
databases/corus_parameter_map_b0040.py
databases/corus_parameter_map_b0041.py
databases/corus_parameter_map_b0042.py
databases/corus_parameter_map_g0003.py
databases/corus_parameter_map_i0002.py
databases/corus_parameter_map_m1000.py
databases/corus_parameter_map_m5B00.py
databases/corus_parameter_map_m5b04.py
databases/corus_parameter_map_v0035.py
databases/corus_parameter_map_v0038.py
databases/corus_parameter_map_v0200.py
databases/corus_parameter_map_v0201.py
databases/corus_parameter_map_v1001.py
databases/corus_parameter_map_v1002.py
iflag/__init__.py
iflag/client.py
iflag/data.py
iflag/exceptions.py
iflag/messages.py
iflag/parse.py
iflag/transport.py
iflag/utils.py
iflag-1.0.1.dist-info/LICENSE.txt
iflag-1.0.1.dist-info/METADATA
iflag-1.0.1.dist-info/RECORD
iflag-1.0.1.dist-info/WHEEL
iflag-1.0.1.dist-info/top_level.txt
